pixtreme_filter/__init__.py
pixtreme_filter/_kernel_utils.py
pixtreme_filter/bilateral.py
pixtreme_filter/box.py
pixtreme_filter/box_filter.py
pixtreme_filter/canny.py
pixtreme_filter/dog.py
pixtreme_filter/gaussian.py
pixtreme_filter/harris_corner.py
pixtreme_filter/histogram.py
pixtreme_filter/laplacian.py
pixtreme_filter/median.py
pixtreme_filter/sobel.py
pixtreme_filter/template_matching.py
pixtreme_filter/unsharp.py
pixtreme_filter/white_balance.py
pixtreme_filter/morphology/__init__.py
pixtreme_filter/morphology/_kernels.py
pixtreme_filter/morphology/dilate.py
pixtreme_filter/morphology/erode.py
pixtreme_filter/morphology/operations.py
pixtreme_filter-0.8.6.dist-info/METADATA
pixtreme_filter-0.8.6.dist-info/WHEEL
pixtreme_filter-0.8.6.dist-info/licenses/LICENSE
pixtreme_filter-0.8.6.dist-info/RECORD
